bottery/__init__.py
bottery/__main__.py
bottery/bottery.py
bottery/cli.py
bottery/exceptions.py
bottery/handlers.py
bottery/log.py
bottery/message.py
bottery/patterns.py
bottery/utils.py
bottery/wsgi.py
bottery/conf/__init__.py
bottery/conf/global_settings.py
bottery/conf/project_template/handlers.py-tpl
bottery/conf/project_template/settings.py-tpl
bottery/conf/project_template/views.py-tpl
bottery/conf/project_template/wsgi.py-tpl
bottery/platform/__init__.py
bottery/platform/messenger/__init__.py
bottery/platform/messenger/api.py
bottery/platform/messenger/engine.py
bottery/platform/telegram/__init__.py
bottery/platform/telegram/api.py
bottery/platform/telegram/engine.py
bottery/platform/telegram/widgets.py
bottery-0.1.1.dist-info/METADATA
bottery-0.1.1.dist-info/RECORD
bottery-0.1.1.dist-info/WHEEL
bottery-0.1.1.dist-info/entry_points.txt
bottery-0.1.1.dist-info/top_level.txt
