Metadata-Version: 2.1
Name: bottery
Version: 0.1.1
Summary: A bot framework with batteries included
Home-page: https://github.com/rougeth/bottery
Author: Marco Rougeth
Author-email: marco@rougeth.com
License: MIT
Platform: UNKNOWN
Classifier: Development Status :: 2 - Pre-Alpha
Classifier: Intended Audience :: Developers
Classifier: License :: OSI Approved :: MIT License
Classifier: Operating System :: POSIX
Classifier: Operating System :: Microsoft :: Windows
Classifier: Operating System :: MacOS :: MacOS X
Classifier: Topic :: Software Development :: User Interfaces
Classifier: Topic :: Utilities
Classifier: Programming Language :: Python :: 3.5
Classifier: Programming Language :: Python :: 3.6
Provides-Extra: dev
Requires-Dist: aiohttp
Requires-Dist: attrs
Requires-Dist: click
Requires-Dist: halo
Requires-Dist: jinja2
Requires-Dist: requests
Provides-Extra: dev
Requires-Dist: coverage; extra == 'dev'
Requires-Dist: flake8; extra == 'dev'
Requires-Dist: isort; extra == 'dev'
Requires-Dist: pytest; extra == 'dev'
Requires-Dist: pytest-aiohttp; extra == 'dev'
Requires-Dist: pytest-asyncio; extra == 'dev'
Requires-Dist: pytest-cov; extra == 'dev'
Requires-Dist: pytest-lazy-fixture; extra == 'dev'
Requires-Dist: pytest-mock; extra == 'dev'
Requires-Dist: sphinx; extra == 'dev'
Requires-Dist: testfixtures; extra == 'dev'
